<?xml version="1.0" encoding="iso-8859-1" ?><sroxml>   <versao>1.0</versao>   <qtd>1</qtd>   <TipoPesquisa>Lista de Objetos</TipoPesquisa>   <TipoResultado>Todos os eventos</TipoResultado>     <objeto>       <numero>PG813782360BR</numero>       <evento>          <tipo>DO</tipo>          <status>01</status>          <data>15/07/2014</data>          <hora>08:25</hora>          <descricao>Objeto encaminhado</descricao>          <local>AGF BAIRRO ITOUPAVA NORTE</local>          <codigo>89052972</codigo>          <cidade>BLUMENAU</cidade>          <uf>SC</uf>          <sto>00235773</sto>       <destino>          <local>CTE FLORIANOPOLIS/GTURN3 (BLUMENAU)</local>          <codigo>89015971</codigo>          <cidade>BLUMENAU</cidade>          <bairro>VORSTADT</bairro>          <uf>SC</uf>       </destino>      </evento>       <evento>          <tipo>PO</tipo>          <status>01</status>          <data>14/07/2014</data>          <hora>16:01</hora>          <descricao>Objeto postado</descricao>          <local>AGF BAIRRO ITOUPAVA NORTE</local>          <codigo>89052972</codigo>          <cidade>BLUMENAU</cidade>          <uf>SC</uf>          <sto>00235773</sto>      </evento>     </objeto></sroxml>